tsugu_uds/__init__.py
tsugu_uds/cli.py
tsugu_uds/database.py
tsugu_uds/server.py
tsugu_uds/handlers/__init__.py
tsugu_uds/handlers/user_handlers.py
tsugu_uds-1.0.9.dist-info/METADATA
tsugu_uds-1.0.9.dist-info/WHEEL
tsugu_uds-1.0.9.dist-info/entry_points.txt
tsugu_uds-1.0.9.dist-info/top_level.txt
tsugu_uds-1.0.9.dist-info/RECORD
