Metadata-Version: 2.4
Name: tsugu-uds
Version: 1.0.9
Summary: Tsugu User Data Server CLI Tool
Author: kumoSleeping
Project-URL: Homepage, https://github.com/kumoSleeping/tsugu-user-data-server
Project-URL: Repository, https://github.com/kumoSleeping/tsugu-user-data-server.git
Classifier: Development Status :: 4 - Beta
Classifier: Intended Audience :: Developers
Classifier: License :: OSI Approved :: MIT License
Classifier: Programming Language :: Python :: 3
Classifier: Programming Language :: Python :: 3.8
Classifier: Programming Language :: Python :: 3.9
Classifier: Programming Language :: Python :: 3.10
Classifier: Programming Language :: Python :: 3.11
Classifier: Programming Language :: Python :: 3.12
Requires-Python: >=3.8
Requires-Dist: typer>=0.9.0
Requires-Dist: rich>=13.0.0
Requires-Dist: quart>=0.19.0
Requires-Dist: loguru>=0.7.0
Requires-Dist: httpx>=0.25.0
Requires-Dist: PyYAML>=6.0
Requires-Dist: uvicorn[standard]>=0.23.0
Provides-Extra: dev
Requires-Dist: black>=23.0.0; extra == "dev"
Requires-Dist: flake8>=6.0.0; extra == "dev"
